{
  "customer_id": "cus-1026",
  "first_name": "Марианна",
  "last_name": "Абрамова",
  "email": "ljubim_1973@example.com",
  "phone": "82255945331",
  "birth_date": "1969-08-04",
  "gender": "female",
  "registration_date": "2025-09-04T12:41:38.387846",
  "is_loyalty_member": true,
  "loyalty_card_number": "LOYAL-9F4A650FDD",
  "purchase_location": {
    "country": "Россия",
    "city": "клх Сузун",
    "street": "алл. Баумана",
    "house": "9",
    "postal_code": "363519",
    "coordinates": {
      "latitude": -23.953326,
      "longitude": 175.677275
    }
  },
  "delivery_address": {
    "country": "Россия",
    "city": "клх Сузун",
    "street": "ул. 9 мая",
    "house": "9",
    "apartment": "55",
    "postal_code": "508296"
  },
  "preferences": {
    "preferred_language": "ru",
    "preferred_payment_method": "card",
    "receive_promotions": true
  }
}